pydisque/__init__.py
pydisque/client.py
pydisque_dwq-0.1.4.dist-info/DESCRIPTION.rst
pydisque_dwq-0.1.4.dist-info/METADATA
pydisque_dwq-0.1.4.dist-info/RECORD
pydisque_dwq-0.1.4.dist-info/WHEEL
pydisque_dwq-0.1.4.dist-info/metadata.json
pydisque_dwq-0.1.4.dist-info/top_level.txt
